initex/__init__.py
initex/main.py
initex-0.0.3.dist-info/METADATA
initex-0.0.3.dist-info/WHEEL
initex-0.0.3.dist-info/top_level.txt
initex-0.0.3.dist-info/RECORD
