Metadata-Version: 2.1
Name: initex
Version: 0.0.3
Summary: A package for initializing text files
